bot_studio_private
