Metadata-Version: 2.1
Name: bot-studio-private
Version: 1.0.1
Summary: Automation Library
Home-page: UNKNOWN
Author: DataKund
Author-email: datakund@gmail.com
License: Apache License 2.0
Platform: UNKNOWN
